LICENSE.txt
README.md
setup.py
src/javaman/__init__.py
src/javaman/connexio.py
src/javaman/errors.py
src/javaman/fb_consultes.py
src/javaman.egg-info/PKG-INFO
src/javaman.egg-info/SOURCES.txt
src/javaman.egg-info/dependency_links.txt
src/javaman.egg-info/requires.txt
src/javaman.egg-info/top_level.txt
src/javaman/accions/__init__.py
src/javaman/accions/albarans.py
src/javaman/accions/articles.py
src/javaman/accions/clients.py
src/javaman/accions/comandes.py
src/javaman/accions/condicions_pagament.py
src/javaman/accions/empreses.py
src/javaman/accions/factures.py
src/javaman/accions/magatzems.py
src/javaman/accions/pobles.py
src/javaman/accions/portals_web.py
src/javaman/accions/proveidors.py
src/javaman/accions/provincies.py
src/javaman/accions/punts_venda.py
src/javaman/accions/recepcions.py
src/javaman/accions/regularitzacions.py
src/javaman/accions/repartidors.py
src/javaman/accions/tarifes.py
src/javaman/accions/tercers.py
src/javaman/accions/usuaris.py
src/javaman/accions/wms.py