Metadata-Version: 2.1
Name: javaman
Version: 1.0.78
Summary: A Girotec - Api project
Author: Girotec
Author-email: info@girotec.es
Requires-Python: >=3.6, <4
License-File: LICENSE.txt
